{
    "p01": {
        "name": "Kkura",
        "phone": "0357933544",
        "gender": "Male",
        "thumnail": "",
        "image": ""
    },
    "p02": {
        "name": "Kkura1",
        "phone": "0357933544",
        "gender": "Male",
        "thumnail": "",
        "image": ""
    },
    "p03": {
        "name": "Kkura2",
        "phone": "0357933544",
        "gender": "Male",
        "thumnail": "",
        "image": ""
    },
    "p04": {
        "name": "Kkura3",
        "phone": "0357933544",
        "gender": "Female",
        "thumnail": "",
        "image": ""
    }
}